[
  {
    "timestamp": "2026-02-23T15:01:25.210450",
    "platform": "facebook",
    "content": {
      "message": "🎉 Exciting News!\n\nWe're thrilled to announce our new AI-driven web development services!\n\n✅ Faster delivery times\n✅ Higher quality code\n✅ Better customer support\n\n📞 +92-300-1234567\n🌐 www.yourbusiness.com\n\n#WebDev #AI #Pakistan #Tech",
      "page_id": "test_page_123"
    },
    "result": {
      "success": true,
      "dry_run": true,
      "message": "[DRY RUN] Would post: \"🎉 Exciting News!\n\nWe're thrilled to announce our new AI-driven web development services!\n\n✅ Faster d...\"",
      "page_id": "test_page_123"
    }
  },
  {
    "timestamp": "2026-02-23T15:01:52.470715",
    "platform": "facebook",
    "content": {
      "message": "🎉 Exciting News!\n\nWe're thrilled to announce our new AI-driven web development services!\n\n✅ Faster delivery times\n✅ Higher quality code\n✅ Better customer support\n\n📞 +92-300-1234567\n🌐 www.yourbusiness.com\n\n#WebDev #AI #Pakistan #Tech",
      "page_id": "test_page_123"
    },
    "result": {
      "success": true,
      "dry_run": true,
      "message": "[DRY RUN] Would post: \"🎉 Exciting News!\n\nWe're thrilled to announce our new AI-driven web development services!\n\n✅ Faster d...\"",
      "page_id": "test_page_123"
    }
  },
  {
    "timestamp": "2026-02-23T15:01:54.521793",
    "platform": "instagram",
    "content": {
      "caption": "🚀 Transform your business with AI-powered solutions!\n\n#WebDevelopment #AI #Tech #Pakistan #Business #Innovation #DigitalTransformation",
      "account_id": "test_account_123"
    },
    "result": {
      "success": true,
      "dry_run": true,
      "message": "[DRY RUN] Would post: \"🚀 Transform your business with AI-powered solutions!\n\n#WebDevelopment #AI #Tech #Pakistan #Business ...\"",
      "account_id": "test_account_123"
    }
  },
  {
    "timestamp": "2026-02-23T15:02:13.922561",
    "platform": "facebook",
    "content": {
      "message": "🎉 Exciting News!\n\nWe're thrilled to announce our new AI-driven web development services!\n\n✅ Faster delivery times\n✅ Higher quality code\n✅ Better customer support\n\n📞 +92-300-1234567\n🌐 www.yourbusiness.com\n\n#WebDev #AI #Pakistan #Tech",
      "page_id": "test_page_123"
    },
    "result": {
      "success": true,
      "dry_run": true,
      "message": "[DRY RUN] Would post: \"🎉 Exciting News!\n\nWe're thrilled to announce our new AI-driven web development services!\n\n✅ Faster d...\"",
      "page_id": "test_page_123"
    }
  },
  {
    "timestamp": "2026-02-23T15:02:15.969115",
    "platform": "instagram",
    "content": {
      "caption": "🚀 Transform your business with AI-powered solutions!\n\n#WebDevelopment #AI #Tech #Pakistan #Business #Innovation #DigitalTransformation",
      "account_id": "test_account_123"
    },
    "result": {
      "success": true,
      "dry_run": true,
      "message": "[DRY RUN] Would post: \"🚀 Transform your business with AI-powered solutions!\n\n#WebDevelopment #AI #Tech #Pakistan #Business ...\"",
      "account_id": "test_account_123"
    }
  },
  {
    "timestamp": "2026-02-23T15:02:40.375126",
    "platform": "facebook",
    "content": {
      "message": "🎉 Exciting News!\n\nWe're thrilled to announce our new AI-driven web development services!\n\n✅ Faster delivery times\n✅ Higher quality code\n✅ Better customer support\n\n📞 +92-300-1234567\n🌐 www.yourbusiness.com\n\n#WebDev #AI #Pakistan #Tech",
      "page_id": "test_page_123"
    },
    "result": {
      "success": true,
      "dry_run": true,
      "message": "[DRY RUN] Would post: \"🎉 Exciting News!\n\nWe're thrilled to announce our new AI-driven web development services!\n\n✅ Faster d...\"",
      "page_id": "test_page_123"
    }
  },
  {
    "timestamp": "2026-02-23T15:02:42.423871",
    "platform": "instagram",
    "content": {
      "caption": "🚀 Transform your business with AI-powered solutions!\n\n#WebDevelopment #AI #Tech #Pakistan #Business #Innovation #DigitalTransformation",
      "account_id": "test_account_123"
    },
    "result": {
      "success": true,
      "dry_run": true,
      "message": "[DRY RUN] Would post: \"🚀 Transform your business with AI-powered solutions!\n\n#WebDevelopment #AI #Tech #Pakistan #Business ...\"",
      "account_id": "test_account_123"
    }
  },
  {
    "timestamp": "2026-02-23T15:04:17.563447",
    "platform": "facebook",
    "content": {
      "message": "🎉 Exciting News!\n\nWe're thrilled to announce our new AI-driven web development services!\n\n✅ Faster delivery times\n✅ Higher quality code\n✅ Better customer support\n\n📞 +92-300-1234567\n🌐 www.yourbusiness.com\n\n#WebDev #AI #Pakistan #Tech",
      "page_id": "test_page_123"
    },
    "result": {
      "success": true,
      "dry_run": true,
      "message": "[DRY RUN] Would post: \"🎉 Exciting News!\n\nWe're thrilled to announce our new AI-driven web development services!\n\n✅ Faster d...\"",
      "page_id": "test_page_123"
    }
  },
  {
    "timestamp": "2026-02-23T15:04:19.633955",
    "platform": "instagram",
    "content": {
      "caption": "🚀 Transform your business with AI-powered solutions!\n\n#WebDevelopment #AI #Tech #Pakistan #Business #Innovation #DigitalTransformation",
      "account_id": "test_account_123"
    },
    "result": {
      "success": true,
      "dry_run": true,
      "message": "[DRY RUN] Would post: \"🚀 Transform your business with AI-powered solutions!\n\n#WebDevelopment #AI #Tech #Pakistan #Business ...\"",
      "account_id": "test_account_123"
    }
  },
  {
    "timestamp": "2026-02-23T15:04:55.534528",
    "platform": "facebook",
    "content": {
      "message": "🎉 Exciting News!\n\nWe're thrilled to announce our new AI-driven web development services!\n\n✅ Faster delivery times\n✅ Higher quality code\n✅ Better customer support\n\n📞 +92-300-1234567\n🌐 www.yourbusiness.com\n\n#WebDev #AI #Pakistan #Tech",
      "page_id": "test_page_123"
    },
    "result": {
      "success": true,
      "dry_run": true,
      "message": "[DRY RUN] Would post: \"🎉 Exciting News!\n\nWe're thrilled to announce our new AI-driven web development services!\n\n✅ Faster d...\"",
      "page_id": "test_page_123"
    }
  },
  {
    "timestamp": "2026-02-23T15:04:57.585463",
    "platform": "instagram",
    "content": {
      "caption": "🚀 Transform your business with AI-powered solutions!\n\n#WebDevelopment #AI #Tech #Pakistan #Business #Innovation #DigitalTransformation",
      "account_id": "test_account_123"
    },
    "result": {
      "success": true,
      "dry_run": true,
      "message": "[DRY RUN] Would post: \"🚀 Transform your business with AI-powered solutions!\n\n#WebDevelopment #AI #Tech #Pakistan #Business ...\"",
      "account_id": "test_account_123"
    }
  },
  {
    "timestamp": "2026-02-23T15:05:52.608526",
    "platform": "facebook",
    "content": {
      "message": "🎉 Exciting News!\n\nWe're thrilled to announce our new AI-driven web development services!\n\n✅ Faster delivery times\n✅ Higher quality code\n✅ Better customer support\n\n📞 +92-300-1234567\n🌐 www.yourbusiness.com\n\n#WebDev #AI #Pakistan #Tech",
      "page_id": "test_page_123"
    },
    "result": {
      "success": true,
      "dry_run": true,
      "message": "[DRY RUN] Would post: \"🎉 Exciting News!\n\nWe're thrilled to announce our new AI-driven web development services!\n\n✅ Faster d...\"",
      "page_id": "test_page_123"
    }
  },
  {
    "timestamp": "2026-02-23T15:05:54.668906",
    "platform": "instagram",
    "content": {
      "caption": "🚀 Transform your business with AI-powered solutions!\n\n#WebDevelopment #AI #Tech #Pakistan #Business #Innovation #DigitalTransformation",
      "account_id": "test_account_123"
    },
    "result": {
      "success": true,
      "dry_run": true,
      "message": "[DRY RUN] Would post: \"🚀 Transform your business with AI-powered solutions!\n\n#WebDevelopment #AI #Tech #Pakistan #Business ...\"",
      "account_id": "test_account_123"
    }
  },
  {
    "timestamp": "2026-02-23T17:12:16.090793",
    "platform": "facebook",
    "content": {
      "message": "🎉 Exciting News!\n\nWe're thrilled to announce our new AI-driven web development services!\n\n✅ Faster delivery times\n✅ Higher quality code\n✅ Better customer support\n\n📞 +92-300-1234567\n🌐 www.yourbusiness.com\n\n#WebDev #AI #Pakistan #Tech",
      "page_id": "test_page_123"
    },
    "result": {
      "success": true,
      "dry_run": true,
      "message": "[DRY RUN] Would post: \"🎉 Exciting News!\n\nWe're thrilled to announce our new AI-driven web development services!\n\n✅ Faster d...\"",
      "page_id": "test_page_123"
    }
  },
  {
    "timestamp": "2026-02-23T17:12:18.156103",
    "platform": "instagram",
    "content": {
      "caption": "🚀 Transform your business with AI-powered solutions!\n\n#WebDevelopment #AI #Tech #Pakistan #Business #Innovation #DigitalTransformation",
      "account_id": "test_account_123"
    },
    "result": {
      "success": true,
      "dry_run": true,
      "message": "[DRY RUN] Would post: \"🚀 Transform your business with AI-powered solutions!\n\n#WebDevelopment #AI #Tech #Pakistan #Business ...\"",
      "account_id": "test_account_123"
    }
  },
  {
    "timestamp": "2026-02-23T17:14:20.078077",
    "platform": "facebook",
    "content": {
      "message": "🎉 Exciting News!\n\nWe're thrilled to announce our new AI-driven web development services!\n\n✅ Faster delivery times\n✅ Higher quality code\n✅ Better customer support\n\n📞 +92-300-1234567\n🌐 www.yourbusiness.com\n\n#WebDev #AI #Pakistan #Tech",
      "page_id": "test_page_123"
    },
    "result": {
      "success": true,
      "dry_run": true,
      "message": "[DRY RUN] Would post: \"🎉 Exciting News!\n\nWe're thrilled to announce our new AI-driven web development services!\n\n✅ Faster d...\"",
      "page_id": "test_page_123"
    }
  },
  {
    "timestamp": "2026-02-23T17:14:22.160678",
    "platform": "instagram",
    "content": {
      "caption": "🚀 Transform your business with AI-powered solutions!\n\n#WebDevelopment #AI #Tech #Pakistan #Business #Innovation #DigitalTransformation",
      "account_id": "test_account_123"
    },
    "result": {
      "success": true,
      "dry_run": true,
      "message": "[DRY RUN] Would post: \"🚀 Transform your business with AI-powered solutions!\n\n#WebDevelopment #AI #Tech #Pakistan #Business ...\"",
      "account_id": "test_account_123"
    }
  },
  {
    "timestamp": "2026-02-23T17:22:25.624275",
    "platform": "facebook",
    "content": {
      "message": "🎉 Exciting News!\n\nWe're thrilled to announce our new AI-driven web development services!\n\n✅ Faster delivery times\n✅ Higher quality code\n✅ Better customer support\n\n📞 +92-300-1234567\n🌐 www.yourbusiness.com\n\n#WebDev #AI #Pakistan #Tech",
      "page_id": "test_page_123"
    },
    "result": {
      "success": true,
      "dry_run": true,
      "message": "[DRY RUN] Would post: \"🎉 Exciting News!\n\nWe're thrilled to announce our new AI-driven web development services!\n\n✅ Faster d...\"",
      "page_id": "test_page_123"
    }
  },
  {
    "timestamp": "2026-02-23T17:22:27.688024",
    "platform": "instagram",
    "content": {
      "caption": "🚀 Transform your business with AI-powered solutions!\n\n#WebDevelopment #AI #Tech #Pakistan #Business #Innovation #DigitalTransformation",
      "account_id": "test_account_123"
    },
    "result": {
      "success": true,
      "dry_run": true,
      "message": "[DRY RUN] Would post: \"🚀 Transform your business with AI-powered solutions!\n\n#WebDevelopment #AI #Tech #Pakistan #Business ...\"",
      "account_id": "test_account_123"
    }
  },
  {
    "timestamp": "2026-02-23T17:37:58.771299",
    "platform": "facebook",
    "content": {
      "message": "🎉 Exciting News!\n\nWe are thrilled to announce our new AI-driven web development services!",
      "page_id": "106665648626271"
    },
    "result": {
      "success": true,
      "dry_run": true,
      "message": "[DRY RUN] Would post: \"🎉 Exciting News!\n\nWe are thrilled to announce our new AI-driven web development services!...\"",
      "page_id": "106665648626271"
    }
  },
  {
    "timestamp": "2026-02-23T17:41:10.044949",
    "platform": "facebook",
    "content": {
      "message": "🎉 Exciting News!\n\nWe are thrilled to announce our new AI-driven web development services!",
      "page_id": "106665648626271"
    },
    "result": {
      "success": true,
      "dry_run": true,
      "message": "[DRY RUN] Would post: \"🎉 Exciting News!\n\nWe are thrilled to announce our new AI-driven web development services!...\"",
      "page_id": "106665648626271"
    }
  },
  {
    "timestamp": "2026-02-23T17:52:36.641561",
    "platform": "facebook",
    "content": {
      "message": "🎉 Exciting News!\n\nWe are thrilled to announce our new AI-driven web development services!",
      "page_id": "106665648626271"
    },
    "result": {
      "success": true,
      "dry_run": true,
      "message": "[DRY RUN] Would post: \"🎉 Exciting News!\n\nWe are thrilled to announce our new AI-driven web development services!...\"",
      "page_id": "106665648626271"
    }
  },
  {
    "timestamp": "2026-02-24T11:19:31.522236",
    "platform": "facebook",
    "content": {
      "message": "🎉 Exciting News!\n\nWe're thrilled to announce our new AI-driven web development services!\n\n✅ Faster delivery times\n✅ Higher quality code\n✅ Better customer support\n\n📞 +92-300-1234567\n🌐 www.yourbusiness.com\n\n#WebDev #AI #Pakistan #Tech",
      "page_id": "test_page_123"
    },
    "result": {
      "success": true,
      "dry_run": true,
      "message": "[DRY RUN] Would post: \"🎉 Exciting News!\n\nWe're thrilled to announce our new AI-driven web development services!\n\n✅ Faster d...\"",
      "page_id": "test_page_123"
    }
  },
  {
    "timestamp": "2026-02-24T11:19:33.842725",
    "platform": "instagram",
    "content": {
      "caption": "🚀 Transform your business with AI-powered solutions!\n\n#WebDevelopment #AI #Tech #Pakistan #Business #Innovation #DigitalTransformation",
      "account_id": "test_account_123"
    },
    "result": {
      "success": true,
      "dry_run": true,
      "message": "[DRY RUN] Would post: \"🚀 Transform your business with AI-powered solutions!\n\n#WebDevelopment #AI #Tech #Pakistan #Business ...\"",
      "account_id": "test_account_123"
    }
  },
  {
    "timestamp": "2026-02-24T11:28:39.601473",
    "platform": "facebook",
    "content": {
      "message": "🎉 Exciting News!\n\nWe're thrilled to announce our new AI-driven web development services!\n\n✅ Faster delivery times\n✅ Higher quality code\n✅ Better customer support\n\n📞 +92-300-1234567\n🌐 www.yourbusiness.com\n\n#WebDev #AI #Pakistan #Tech",
      "page_id": "test_page_123"
    },
    "result": {
      "success": true,
      "dry_run": true,
      "message": "[DRY RUN] Would post: \"🎉 Exciting News!\n\nWe're thrilled to announce our new AI-driven web development services!\n\n✅ Faster d...\"",
      "page_id": "test_page_123"
    }
  },
  {
    "timestamp": "2026-02-24T11:28:41.645526",
    "platform": "instagram",
    "content": {
      "caption": "🚀 Transform your business with AI-powered solutions!\n\n#WebDevelopment #AI #Tech #Pakistan #Business #Innovation #DigitalTransformation",
      "account_id": "test_account_123"
    },
    "result": {
      "success": true,
      "dry_run": true,
      "message": "[DRY RUN] Would post: \"🚀 Transform your business with AI-powered solutions!\n\n#WebDevelopment #AI #Tech #Pakistan #Business ...\"",
      "account_id": "test_account_123"
    }
  },
  {
    "timestamp": "2026-02-24T11:31:33.733144",
    "platform": "instagram",
    "content": {
      "caption": "🚀 Transform your business with AI-powered solutions!",
      "account_id": "17841436842078450"
    },
    "result": {
      "success": false,
      "error": "Error validating access token: Session has expired on Monday, 23-Feb-26 05:00:00 PST. The current time is Monday, 23-Feb-26 22:31:33 PST."
    }
  },
  {
    "timestamp": "2026-02-24T11:35:33.202180",
    "platform": "facebook",
    "content": {
      "message": "🎉 Exciting News!\n\nWe're thrilled to announce our new AI-driven web development services!\n\n✅ Faster delivery times\n✅ Higher quality code\n✅ Better customer support\n\n📞 +92-300-1234567\n🌐 www.yourbusiness.com\n\n#WebDev #AI #Pakistan #Tech",
      "page_id": "test_page_123"
    },
    "result": {
      "success": true,
      "dry_run": true,
      "message": "[DRY RUN] Would post: \"🎉 Exciting News!\n\nWe're thrilled to announce our new AI-driven web development services!\n\n✅ Faster d...\"",
      "page_id": "test_page_123"
    }
  },
  {
    "timestamp": "2026-02-24T11:35:35.270369",
    "platform": "instagram",
    "content": {
      "caption": "🚀 Transform your business with AI-powered solutions!\n\n#WebDevelopment #AI #Tech #Pakistan #Business #Innovation #DigitalTransformation",
      "account_id": "test_account_123"
    },
    "result": {
      "success": true,
      "dry_run": true,
      "message": "[DRY RUN] Would post: \"🚀 Transform your business with AI-powered solutions!\n\n#WebDevelopment #AI #Tech #Pakistan #Business ...\"",
      "account_id": "test_account_123"
    }
  },
  {
    "timestamp": "2026-02-24T11:37:00.555746",
    "platform": "instagram",
    "content": {
      "caption": "🚀 Transform your business with AI-powered solutions!",
      "account_id": "17841436842078450"
    },
    "result": {
      "success": false,
      "error": "Error validating access token: Session has expired on Monday, 23-Feb-26 05:00:00 PST. The current time is Monday, 23-Feb-26 22:37:00 PST."
    }
  },
  {
    "timestamp": "2026-02-24T11:39:29.386634",
    "platform": "instagram",
    "content": {
      "caption": "🚀 Transform your business with AI-powered solutions!",
      "account_id": "17841436842078450"
    },
    "result": {
      "success": false,
      "error": "Error validating access token: Session has expired on Monday, 23-Feb-26 05:00:00 PST. The current time is Monday, 23-Feb-26 22:39:28 PST."
    }
  },
  {
    "timestamp": "2026-02-24T11:43:18.579698",
    "platform": "instagram",
    "content": {
      "caption": "🚀 Transform your business with AI-powered solutions!",
      "account_id": "17841436842078450"
    },
    "result": {
      "success": false,
      "error": "Error validating access token: Session has expired on Monday, 23-Feb-26 05:00:00 PST. The current time is Monday, 23-Feb-26 22:43:18 PST."
    }
  },
  {
    "timestamp": "2026-02-24T11:46:25.562357",
    "platform": "instagram",
    "content": {
      "caption": "🚀 Transform your business with AI-powered solutions!",
      "account_id": "17841436842078450"
    },
    "result": {
      "success": false,
      "error": "Any of the pages_read_engagement, pages_manage_metadata,\n        pages_read_user_content, pages_manage_ads, pages_show_list or\n        pages_messaging permission(s) must be granted before impersonating a\n        user's page."
    }
  },
  {
    "timestamp": "2026-02-24T11:50:46.323613",
    "platform": "instagram",
    "content": {
      "caption": "🚀 Transform your business with AI-powered solutions!",
      "account_id": "17841436842078450"
    },
    "result": {
      "success": false,
      "error": "Unsupported post request. Object with ID '17841436842078450' does not exist, cannot be loaded due to missing permissions, or does not support this operation. Please read the Graph API documentation at https://developers.facebook.com/docs/graph-api"
    }
  },
  {
    "timestamp": "2026-02-24T12:03:33.361522",
    "platform": "instagram",
    "content": {
      "caption": "🚀 Transform your business with AI-powered solutions!",
      "account_id": "17841436842078450"
    },
    "result": {
      "success": false,
      "error": "Unsupported post request. Object with ID '17841436842078450' does not exist, cannot be loaded due to missing permissions, or does not support this operation. Please read the Graph API documentation at https://developers.facebook.com/docs/graph-api"
    }
  },
  {
    "timestamp": "2026-02-24T12:05:45.211804",
    "platform": "instagram",
    "content": {
      "caption": "🚀 Transform your business with AI-powered solutions!",
      "account_id": "17841436842078450"
    },
    "result": {
      "success": false,
      "error": "Unsupported post request. Object with ID '17841436842078450' does not exist, cannot be loaded due to missing permissions, or does not support this operation. Please read the Graph API documentation at https://developers.facebook.com/docs/graph-api"
    }
  },
  {
    "timestamp": "2026-02-24T12:08:48.590652",
    "platform": "facebook",
    "content": {
      "message": "🎉 Hello from my AI Employee System!\n\nThis is a test post from my automated MCP integration.\n\n✅ Odoo Accounting\n✅ Social Media Automation\n✅ AI-Driven Workflows\n\n#AI #Tech #Pakistan #Automation",
      "page_id": "110326951910826"
    },
    "result": {
      "success": true,
      "post_id": "110326951910826_891218583823662",
      "message": "Posted via Graph API"
    }
  },
  {
    "timestamp": "2026-02-24T12:08:51.870738",
    "platform": "instagram",
    "content": {
      "caption": "🚀 Transform your business with AI-powered solutions!",
      "account_id": "17841457282813798"
    },
    "result": {
      "success": false,
      "error": "Unsupported post request. Object with ID '17841457282813798' does not exist, cannot be loaded due to missing permissions, or does not support this operation. Please read the Graph API documentation at https://developers.facebook.com/docs/graph-api"
    }
  },
  {
    "timestamp": "2026-02-24T12:10:35.051201",
    "platform": "instagram",
    "content": {
      "caption": "🚀 AI Automation Test!\n\nTesting my MCP integration.\n\n#AI #Tech #Pakistan #Business #Automation",
      "account_id": "17841457182813798"
    },
    "result": {
      "success": false,
      "error": "Only photo or video can be accepted as media type."
    }
  },
  {
    "timestamp": "2026-02-24T12:10:38.662288",
    "platform": "instagram",
    "content": {
      "caption": "🚀 Transform your business with AI-powered solutions!",
      "account_id": "17841457182813798"
    },
    "result": {
      "success": false,
      "error": "Only photo or video can be accepted as media type."
    }
  },
  {
    "timestamp": "2026-02-24T12:11:53.889894",
    "platform": "instagram",
    "content": {
      "caption": "🚀 AI Automation Test!\n\nTesting my MCP integration.\n\n#AI #Tech #Pakistan #Business #Automation",
      "account_id": "17841457182813798"
    },
    "result": {
      "success": false,
      "error": "Only photo or video can be accepted as media type."
    }
  },
  {
    "timestamp": "2026-02-24T12:11:57.260726",
    "platform": "instagram",
    "content": {
      "caption": "🚀 Transform your business with AI-powered solutions!",
      "account_id": "17841457182813798"
    },
    "result": {
      "success": false,
      "error": "Only photo or video can be accepted as media type."
    }
  },
  {
    "timestamp": "2026-02-24T12:17:24.357480",
    "platform": "instagram",
    "content": {
      "caption": "🚀 AI Automation Test!\n\nTesting my MCP integration.\n\n#AI #Tech #Pakistan #Business #Automation",
      "account_id": "17841457182813798"
    },
    "result": {
      "success": true,
      "post_id": "18033131195588415",
      "message": "Posted to Instagram"
    }
  },
  {
    "timestamp": "2026-02-24T12:17:36.724812",
    "platform": "instagram",
    "content": {
      "caption": "🚀 Transform your business with AI-powered solutions!",
      "account_id": "17841457182813798"
    },
    "result": {
      "success": true,
      "post_id": "18104464747865891",
      "message": "Posted to Instagram"
    }
  }
]